sf_pipelines_test/__init__.py
sf_pipelines_test/__main__.py
sf_pipelines_test/annex_a_pipeline/__init__.py
sf_pipelines_test/annex_a_pipeline/cli.py
sf_pipelines_test/annex_a_pipeline/pipeline.py
sf_pipelines_test/annex_a_pipeline/spec/Annex_A_schema.yml
sf_pipelines_test/annex_a_pipeline/spec/__init__.py
sf_pipelines_test/annex_a_pipeline/spec/pipeline.yml
sf_pipelines_test/annex_a_pipeline/spec/samples/Annex_A.xlsx
sf_pipelines_test/annex_a_pipeline/spec/samples/__init__.py
sf_pipelines_test/annex_a_pipeline/stream_filters.py
sf_pipelines_test/annex_a_pipeline/stream_pipeline.py
sf_pipelines_test/cin_census_pipeline/__init__.py
sf_pipelines_test/cin_census_pipeline/_reports_assessment_factors.py
sf_pipelines_test/cin_census_pipeline/_reports_referrals.py
sf_pipelines_test/cin_census_pipeline/pipeline.py
sf_pipelines_test/cin_census_pipeline/reports.py
sf_pipelines_test/cin_census_pipeline/spec/CIN_schema_2017.xsd
sf_pipelines_test/cin_census_pipeline/spec/CIN_schema_2018.xsd
sf_pipelines_test/cin_census_pipeline/spec/CIN_schema_2019.xsd
sf_pipelines_test/cin_census_pipeline/spec/CIN_schema_2020.xsd
sf_pipelines_test/cin_census_pipeline/spec/CIN_schema_2021.xsd
sf_pipelines_test/cin_census_pipeline/spec/CIN_schema_2022.xsd
sf_pipelines_test/cin_census_pipeline/spec/CIN_schema_2023.xsd
sf_pipelines_test/cin_census_pipeline/spec/CIN_schema_2024.xsd
sf_pipelines_test/cin_census_pipeline/spec/__init__.py
sf_pipelines_test/cin_census_pipeline/spec/agg.yml
sf_pipelines_test/cin_census_pipeline/spec/samples/__init__.py
sf_pipelines_test/cin_census_pipeline/spec/samples/cin-2022.xml
sf_pipelines_test/cin_census_pipeline/stream_filters.py
sf_pipelines_test/cin_census_pipeline/stream_parse.py
sf_pipelines_test/cin_census_pipeline/stream_pipeline.py
sf_pipelines_test/cin_census_pipeline/stream_record.py
sf_pipelines_test/common/__init__.py
sf_pipelines_test/common/_fs_serializer.py
sf_pipelines_test/common/_transform_functions.py
sf_pipelines_test/common/archive.py
sf_pipelines_test2-0.1.0.dist-info/METADATA
sf_pipelines_test2-0.1.0.dist-info/WHEEL
sf_pipelines_test2-0.1.0.dist-info/RECORD
